NomDeMonPackage/__init__.py
NomDeMonPackage-0.0.0.dist-info/LICENSE.txt
NomDeMonPackage-0.0.0.dist-info/METADATA
NomDeMonPackage-0.0.0.dist-info/WHEEL
NomDeMonPackage-0.0.0.dist-info/top_level.txt
NomDeMonPackage-0.0.0.dist-info/RECORD
